HyperLibs/__init__.py
HyperLibs/base.py
HyperLibs/button.py
HyperLibs/chat_ai.py
HyperLibs/config.py
HyperLibs/lang.py
v1hyperbot-0.1.1.dist-info/METADATA
v1hyperbot-0.1.1.dist-info/WHEEL
v1hyperbot-0.1.1.dist-info/top_level.txt
v1hyperbot-0.1.1.dist-info/RECORD
